{
  "winners": [
    {
      "user": "0x9B2247E137387C2A2C49e9607e4b70473891E9fc",
      "prizes": {
        "4": [
          25,
          139
        ],
        "5": [
          140,
          631,
          633,
          880,
          999
        ]
      }
    },
    {
      "user": "0xa5c3A513645A9a00cB561fED40438E9DFE0D6a69",
      "prizes": {
        "3": [
          5,
          11,
          18,
          27,
          32,
          57,
          58,
          60
        ],
        "4": [
          7,
          17,
          33,
          43,
          68,
          88,
          98,
          109,
          115,
          130,
          146,
          156,
          178,
          179,
          192,
          208,
          212,
          222,
          224,
          231,
          243,
          250
        ],
        "5": [
          3,
          9,
          57,
          60,
          62,
          65,
          71,
          80,
          112,
          114,
          130,
          135,
          137,
          163,
          169,
          171,
          181,
          183,
          185,
          191,
          198,
          199,
          202,
          208,
          219,
          228,
          270,
          271,
          287,
          289,
          295,
          298,
          312,
          315,
          327,
          332,
          334,
          340,
          344,
          368,
          373,
          374,
          387,
          388,
          392,
          395,
          410,
          411,
          422,
          427,
          445,
          451,
          457,
          460,
          470,
          482,
          502,
          513,
          546,
          547,
          554,
          558,
          561,
          573,
          606,
          618,
          621,
          643,
          646,
          648,
          664,
          674,
          706,
          727,
          728,
          766,
          788,
          793,
          804,
          809,
          821,
          831,
          842,
          845,
          848,
          853,
          867,
          877,
          881,
          890,
          898,
          907,
          909,
          921,
          934,
          951,
          958,
          969,
          973,
          974,
          984,
          989,
          990,
          997,
          1004,
          1020,
          1023
        ]
      }
    },
    {
      "user": "0x75C83356987c8d813829D9FBb5DE504b547750A6",
      "prizes": {
        "4": [
          120
        ]
      }
    },
    {
      "user": "0x0ab871dB12E2fc52c7Ea2d6eA372525e7F7718EB",
      "prizes": {
        "4": [
          207
        ]
      }
    },
    {
      "user": "0x2B9B48BBDd8018396dAAd50364c467246Db30D87",
      "prizes": {
        "3": [
          0,
          18,
          23
        ],
        "4": [
          11,
          190,
          199,
          219,
          242
        ],
        "5": [
          4,
          12,
          19,
          35,
          51,
          109,
          148,
          164,
          165,
          190,
          193,
          197,
          207,
          235,
          261,
          267,
          295,
          304,
          309,
          322,
          368,
          389,
          399,
          405,
          461,
          466,
          482,
          496,
          514,
          532,
          600,
          710,
          782,
          804,
          809,
          961,
          1014
        ]
      }
    },
    {
      "user": "0x2686544Ed0149b134B27009958788cDf4Ca8c064",
      "prizes": {
        "3": [
          17,
          29
        ],
        "4": [
          5,
          6,
          62,
          222
        ],
        "5": [
          0,
          80,
          105,
          127,
          149,
          189,
          196,
          199,
          398,
          434,
          498,
          593,
          614,
          723,
          762,
          805,
          903,
          1013
        ]
      }
    },
    {
      "user": "0x1F335c8aB8514920Dba51a72f39E92B514cBAcef",
      "prizes": {
        "3": [
          0
        ],
        "4": [
          154
        ],
        "5": [
          122,
          258,
          453,
          554,
          695,
          837,
          960,
          991
        ]
      }
    },
    {
      "user": "0x3994537274f3fF3eefc413E0D669b05D6446D46b",
      "prizes": {
        "3": [
          6,
          53
        ],
        "4": [
          21,
          31,
          107,
          188,
          209
        ],
        "5": [
          35,
          76,
          109,
          110,
          129,
          137,
          248,
          297,
          344,
          376,
          424,
          540,
          554,
          646,
          714,
          766,
          783,
          869,
          870,
          894,
          912,
          937,
          987,
          1018
        ]
      }
    },
    {
      "user": "0x1eC1E67F75e66814e5D9Ae5F61CBDaA1472d068E",
      "prizes": {
        "3": [
          59
        ],
        "4": [
          221
        ],
        "5": [
          68,
          292,
          450,
          493,
          873
        ]
      }
    },
    {
      "user": "0x20d801Dbee0505F9a77CFF40f5fed6Ff0f0ee9D6",
      "prizes": {
        "4": [
          2,
          73
        ],
        "5": [
          300,
          444,
          624,
          708,
          739,
          752
        ]
      }
    },
    {
      "user": "0x58412bF2ab618867eC3f13c33c84c35c6EB69e09",
      "prizes": {
        "3": [
          9
        ],
        "4": [
          128,
          152,
          170
        ],
        "5": [
          78,
          117,
          197,
          227,
          253,
          318,
          375,
          492,
          530,
          579,
          664,
          779
        ]
      }
    },
    {
      "user": "0xE09c035a9751b594A6D0dc8a4eF9C1f1139ebad2",
      "prizes": {
        "3": [
          29
        ],
        "4": [
          72,
          227
        ],
        "5": [
          57,
          62,
          76,
          246,
          252,
          255,
          280,
          421,
          426,
          505,
          519,
          535,
          680,
          768,
          926,
          998,
          1017
        ]
      }
    },
    {
      "user": "0x9F36A6bB398118bdCD5B1bC3343D8FEB6d7d02B9",
      "prizes": {
        "4": [
          140,
          168
        ]
      }
    },
    {
      "user": "0xe0e7b7C5aE92Fe94D2ae677D81214D6Ad7A11C27",
      "prizes": {
        "4": [
          101,
          152,
          210
        ],
        "5": [
          64,
          84,
          130,
          202,
          267,
          315,
          378,
          550,
          560,
          615,
          686,
          748,
          889,
          1008,
          1016
        ]
      }
    },
    {
      "user": "0x08DE07fE4B53F315A1C93cA8396c18985432d41E",
      "prizes": {
        "3": [
          50
        ],
        "4": [
          151
        ],
        "5": [
          76,
          88,
          97,
          197,
          261,
          302,
          340,
          357,
          396,
          483,
          488,
          648,
          731,
          847,
          966
        ]
      }
    },
    {
      "user": "0x7928A66320e3799a935a877A70EB8567b7C17A75",
      "prizes": {
        "4": [
          128,
          214,
          223
        ],
        "5": [
          32,
          61,
          78,
          133,
          197,
          366,
          727,
          757,
          953,
          986
        ]
      }
    },
    {
      "user": "0xAAb9e2C2Ec3697D00E33178e52A51A7EB24CC9B1",
      "prizes": {
        "3": [
          39
        ],
        "4": [
          76,
          187,
          203,
          238,
          242
        ],
        "5": [
          31,
          178,
          363,
          422,
          554,
          591,
          660,
          808,
          1010
        ]
      }
    },
    {
      "user": "0xa184aa8488908b43cCf43b5Ef13Ae528693Dfd00",
      "prizes": {
        "3": [
          53
        ],
        "4": [
          18,
          41,
          96,
          101,
          219
        ],
        "5": [
          39,
          58,
          82,
          206,
          225,
          249,
          269,
          271,
          465,
          534,
          651,
          745,
          753,
          849,
          850,
          854,
          892,
          922,
          943
        ]
      }
    },
    {
      "user": "0x9B5A53E376Eddf11B7015680e1f07372f9fc12c4",
      "prizes": {
        "3": [
          28,
          38
        ],
        "4": [
          103,
          195
        ],
        "5": [
          204,
          256,
          307,
          406,
          451,
          533,
          546,
          582,
          637,
          661,
          712,
          865,
          945,
          997
        ]
      }
    },
    {
      "user": "0xAF1bff74708098dB603e48aaEbEC1BBAe03Dcf11",
      "prizes": {
        "3": [
          17,
          34,
          44
        ],
        "4": [
          24,
          71,
          127,
          148,
          150,
          217
        ],
        "5": [
          44,
          122,
          319,
          517,
          660,
          778,
          809,
          863
        ]
      }
    },
    {
      "user": "0x9AA4E6641FEfD0764BfEBDeda637E7782d7eD4dc",
      "prizes": {
        "3": [
          2,
          5,
          7,
          25,
          49
        ],
        "4": [
          7,
          66,
          82,
          124,
          131,
          155,
          158,
          230
        ],
        "5": [
          8,
          41,
          97,
          101,
          137,
          152,
          173,
          177,
          211,
          222,
          247,
          248,
          260,
          361,
          391,
          404,
          505,
          514,
          575,
          644,
          664,
          666,
          703,
          713,
          714,
          727,
          755,
          777,
          944,
          981
        ]
      }
    },
    {
      "user": "0xBD167d37DF42Df3e8E2D4fFBc8993E3100097Ac7",
      "prizes": {
        "3": [
          31
        ],
        "5": [
          222,
          364,
          764,
          792,
          981
        ]
      }
    },
    {
      "user": "0x55A5705453Ee82c742274154136Fce8149597058",
      "prizes": {
        "3": [
          44
        ]
      }
    },
    {
      "user": "0xF58fe388D53E9542F0BDdFF2D1578B13675228FD",
      "prizes": {
        "5": [
          30,
          38,
          622,
          698,
          830
        ]
      }
    },
    {
      "user": "0xAf5B16f740bed90af42Df6C28e5cd79458C102f1",
      "prizes": {
        "5": [
          38,
          366,
          485,
          606,
          632,
          929,
          1014
        ]
      }
    },
    {
      "user": "0xE5860FF1c57DDCEF024Cb43B37b8A20bfE4c9822",
      "prizes": {
        "5": [
          338
        ]
      }
    },
    {
      "user": "0x175c4f84F41bD3Dc37a42d8260F57bC5475e9753",
      "prizes": {
        "5": [
          254,
          393
        ]
      }
    },
    {
      "user": "0x7692A4436F8252f34258C2bFA846eC5E840D5e55",
      "prizes": {
        "5": [
          171,
          673,
          702,
          748,
          769
        ]
      }
    },
    {
      "user": "0x4e42Bd9e46444146C6Ae31Bc301F0Ab7CF623eE7",
      "prizes": {
        "5": [
          273,
          766
        ]
      }
    },
    {
      "user": "0x57a482EA32c7F75A9C0734206f5BD4f9BCb38e12",
      "prizes": {
        "5": [
          64
        ]
      }
    },
    {
      "user": "0x59de64f518f99B310e8e0014823B08E849eB7A24",
      "prizes": {
        "5": [
          150
        ]
      }
    },
    {
      "user": "0xB44B6442B731D9954819470f6f528aa3E65dFF15",
      "prizes": {
        "5": [
          714
        ]
      }
    },
    {
      "user": "0xcf47ddc278E28D8eC8d3B2864553054DaA5FAD67",
      "prizes": {
        "5": [
          469
        ]
      }
    },
    {
      "user": "0x7AEAfb0aF089bEE3a98519E13054849De04d08Ab",
      "prizes": {
        "5": [
          80
        ]
      }
    }
  ]
}