{
  "winners": [
    {
      "user": "0xb525F6b3b5EFCC0C54582de2F08D890F7793e3e4",
      "prizes": {
        "4": [
          80
        ]
      }
    },
    {
      "user": "0x5955037f92e18Abb42dEe44754615d31190B21bB",
      "prizes": {
        "3": [
          9,
          18
        ],
        "4": [
          105
        ],
        "5": [
          222,
          467,
          512,
          844
        ]
      }
    },
    {
      "user": "0x7928A66320e3799a935a877A70EB8567b7C17A75",
      "prizes": {
        "4": [
          208
        ],
        "5": [
          379
        ]
      }
    },
    {
      "user": "0x85Bc77fE4E423142Dd32a2b3B097CAACA4A03172",
      "prizes": {
        "4": [
          16
        ],
        "5": [
          708,
          876
        ]
      }
    },
    {
      "user": "0xfB424B3c08e5D1205C66d5140781BD718f7F9860",
      "prizes": {
        "4": [
          44
        ],
        "5": [
          575,
          596
        ]
      }
    },
    {
      "user": "0x9F36A6bB398118bdCD5B1bC3343D8FEB6d7d02B9",
      "prizes": {
        "4": [
          217
        ],
        "5": [
          823,
          935,
          990
        ]
      }
    },
    {
      "user": "0xe24bC6c67fEF2FFe40283c1359dCE44bd19c72C4",
      "prizes": {
        "4": [
          98
        ],
        "5": [
          19,
          42,
          453,
          524,
          808,
          902,
          974
        ]
      }
    },
    {
      "user": "0x461CdE402c6b945036df1b49F2703fCa22B23d7b",
      "prizes": {
        "4": [
          63
        ],
        "5": [
          162,
          206,
          260,
          344
        ]
      }
    },
    {
      "user": "0x8445271FcA0d979aae411f0B72f4EE9A620D41D7",
      "prizes": {
        "4": [
          245
        ],
        "5": [
          655
        ]
      }
    },
    {
      "user": "0xf05E4F44De569cF8C6aCf5fCe98271008A532969",
      "prizes": {
        "4": [
          107
        ],
        "5": [
          147,
          494
        ]
      }
    },
    {
      "user": "0xe9FBD0A3703A487DbE8FAcb48288dEb267596eAA",
      "prizes": {
        "4": [
          231
        ],
        "5": [
          370,
          1021
        ]
      }
    },
    {
      "user": "0x0857D7771Aa13a0988F7aAc9d72bFEEa6B69d73C",
      "prizes": {
        "3": [
          54
        ],
        "4": [
          119
        ],
        "5": [
          48,
          127,
          361,
          713,
          867,
          924,
          960
        ]
      }
    },
    {
      "user": "0x3994537274f3fF3eefc413E0D669b05D6446D46b",
      "prizes": {
        "4": [
          189
        ],
        "5": [
          135,
          321,
          506,
          680,
          696,
          742,
          1000
        ]
      }
    },
    {
      "user": "0x20c7b705B9312daE30B5A96A61ec6013225595D4",
      "prizes": {
        "4": [
          185
        ],
        "5": [
          671
        ]
      }
    },
    {
      "user": "0x1A2B50BB52B322b50d3266F4Be8e43944D967e94",
      "prizes": {
        "4": [
          70,
          213
        ],
        "5": [
          23,
          97,
          248,
          364,
          513,
          522,
          608
        ]
      }
    },
    {
      "user": "0xf756e4368a03627EAc9B0c474c8420794f429BA1",
      "prizes": {
        "4": [
          48
        ],
        "5": [
          43,
          118,
          270,
          786,
          794
        ]
      }
    },
    {
      "user": "0x841242256730Ef0eC231bA69197a0eC0ec5E9e01",
      "prizes": {
        "4": [
          15
        ],
        "5": [
          712
        ]
      }
    },
    {
      "user": "0xde04d1e25A95b8F9dFE0f8f6fd3748F618187288",
      "prizes": {
        "5": [
          577
        ]
      }
    },
    {
      "user": "0x3Fa25eb9D966F49A4107BBa378Afec5919212622",
      "prizes": {
        "5": [
          266
        ]
      }
    },
    {
      "user": "0x897D24557116F39440FaB68FEB0Ed97BBBeaEeed",
      "prizes": {
        "5": [
          282,
          571,
          669
        ]
      }
    },
    {
      "user": "0x501d66e0B4254dE6187443B9CDB744E2752F489e",
      "prizes": {
        "5": [
          827
        ]
      }
    },
    {
      "user": "0x33b81b6130E0684c140a110d921fA307B48991D6",
      "prizes": {
        "5": [
          135,
          307
        ]
      }
    },
    {
      "user": "0xa7329fD51B2dC832f92A1Ec5e05CC35D4d1a095e",
      "prizes": {
        "5": [
          913,
          936,
          968
        ]
      }
    },
    {
      "user": "0x5c51eC4986e5fC0e92b309602fE288cC00CD822e",
      "prizes": {
        "5": [
          161
        ]
      }
    },
    {
      "user": "0x54DA0d3567A1fFBe2B9E79dC8B5e63ebb9152F09",
      "prizes": {
        "5": [
          470
        ]
      }
    },
    {
      "user": "0x4cd7a2a984ceD0C9f7316b2B4427601E6dB87b30",
      "prizes": {
        "5": [
          634,
          929
        ]
      }
    },
    {
      "user": "0x6808C8F473363D085D8D8Ece4b53966cAD81Ee4A",
      "prizes": {
        "5": [
          818
        ]
      }
    },
    {
      "user": "0x714F68453Ea8cFCF11463D8EE8bc1922a8732Eb1",
      "prizes": {
        "5": [
          530,
          771
        ]
      }
    },
    {
      "user": "0x37D9df5D7Aa7E318e063728Dce72F54563065508",
      "prizes": {
        "5": [
          958
        ]
      }
    },
    {
      "user": "0x67D9057494e2E1B7361251043843Db3c2ABF8177",
      "prizes": {
        "5": [
          1004
        ]
      }
    },
    {
      "user": "0x6c5fE0c4F7443691397E744806684486040c00a4",
      "prizes": {
        "5": [
          52,
          855
        ]
      }
    },
    {
      "user": "0xe524D6514f5c6C91796D223c3310CE211bC749C0",
      "prizes": {
        "5": [
          673,
          741
        ]
      }
    },
    {
      "user": "0xa05F2774bA121531DA7C1bB7fE437AAf881C71b6",
      "prizes": {
        "5": [
          83
        ]
      }
    },
    {
      "user": "0x233998C7a34F26ee25F6299ECf8e26C0EC9e62e4",
      "prizes": {
        "5": [
          407,
          981
        ]
      }
    },
    {
      "user": "0xD917Eb4dCfCCf91E6496702bc6309d5A59EEF713",
      "prizes": {
        "5": [
          974
        ]
      }
    },
    {
      "user": "0x368a3217deD4C5986dB39bCc22932B209Eb17026",
      "prizes": {
        "5": [
          600
        ]
      }
    },
    {
      "user": "0x28458788Fb965BCaC5f0Df629916A3735112dAc6",
      "prizes": {
        "5": [
          30,
          82,
          361
        ]
      }
    },
    {
      "user": "0xf45cE3921F25677802B0f32b1664Ba55535264bE",
      "prizes": {
        "5": [
          454
        ]
      }
    },
    {
      "user": "0xbB0656195430F1F740Dd5f236C024B8d9CE9809b",
      "prizes": {
        "5": [
          334,
          730
        ]
      }
    },
    {
      "user": "0xC1C79C6378e5A72895C8eA15fc6Dd59fFddc8dee",
      "prizes": {
        "5": [
          400
        ]
      }
    },
    {
      "user": "0xDADd6E94b6aB894E536B5eb90A2Bb04bbD4e78B8",
      "prizes": {
        "5": [
          768
        ]
      }
    },
    {
      "user": "0x1200Eb4fA3dF9903fC6EfF1d7A4a5D17502329b2",
      "prizes": {
        "5": [
          313,
          373,
          443,
          461,
          478,
          505,
          555,
          689,
          753,
          857
        ]
      }
    },
    {
      "user": "0xE1EFd0284B2e12d261466D51f421f2d1e930e121",
      "prizes": {
        "5": [
          948
        ]
      }
    },
    {
      "user": "0x9249f2C06c7d69b3B4418FB416900c271F93764A",
      "prizes": {
        "5": [
          684
        ]
      }
    },
    {
      "user": "0x0994E680bCbeC9F3701734F21c4487f05893e104",
      "prizes": {
        "5": [
          881
        ]
      }
    },
    {
      "user": "0x4a3e6E66f8C32bC05A50879f872B1177A1573CDF",
      "prizes": {
        "5": [
          33,
          566,
          1004
        ]
      }
    },
    {
      "user": "0xf0B3424006dFff9c313cEc191a1406fb004dbe3C",
      "prizes": {
        "5": [
          217
        ]
      }
    },
    {
      "user": "0x53315dEb6d95ad7b3863AC97C7aE46E785AbAc52",
      "prizes": {
        "5": [
          362,
          995
        ]
      }
    },
    {
      "user": "0xcC22F7F6A8296ED44f0F0E758374675120909177",
      "prizes": {
        "3": [
          1
        ]
      }
    }
  ]
}