{
  "winners": [
    {
      "user": "0xA249aC7499Bb7A18f47168f936825452d466DcAf",
      "prizes": {
        "3": [
          8,
          30
        ],
        "4": [
          11,
          89,
          98
        ],
        "5": [
          38,
          373,
          406,
          449,
          452,
          833,
          914,
          933
        ]
      }
    },
    {
      "user": "0x9B06ffcB22773A854c0467B2c05f1b5427133be8",
      "prizes": {
        "3": [
          30
        ],
        "4": [
          9
        ],
        "5": [
          38,
          250,
          256,
          583,
          594,
          715,
          874,
          959
        ]
      }
    },
    {
      "user": "0x7928A66320e3799a935a877A70EB8567b7C17A75",
      "prizes": {
        "4": [
          42
        ],
        "5": [
          620
        ]
      }
    },
    {
      "user": "0x3994537274f3fF3eefc413E0D669b05D6446D46b",
      "prizes": {
        "4": [
          230
        ]
      }
    },
    {
      "user": "0xe6F43a9dc80d833decF722dF5d0A2C7e6013eF07",
      "prizes": {
        "4": [
          197,
          206
        ],
        "5": [
          93,
          635
        ]
      }
    },
    {
      "user": "0x07Afb3101e2d29702c10603CcC54498c8e7c48b5",
      "prizes": {
        "5": [
          190,
          730,
          785
        ]
      }
    },
    {
      "user": "0x0E9B063789909565CEdA1Fba162474405A151E66",
      "prizes": {
        "5": [
          855
        ]
      }
    }
  ]
}